copinicoos/__init__.py
copinicoos/__main__.py
copinicoos/account_manager.py
copinicoos/input_manager.py
copinicoos/loggable.py
copinicoos/query_formatter.py
copinicoos/resumable.py
copinicoos/secure.py
copinicoos/wget_check.py
copinicoos/worker.py
copinicoos/worker_manager.py
copinicoos-0.0.2.dist-info/LICENSE
copinicoos-0.0.2.dist-info/METADATA
copinicoos-0.0.2.dist-info/WHEEL
copinicoos-0.0.2.dist-info/top_level.txt
copinicoos-0.0.2.dist-info/RECORD
