Metadata-Version: 2.1
Name: copinicoos
Version: 0.0.2
Summary: Copernicus Download Manager
Home-page: https://github.com/potatowagon/copinicoos
Author: Sherry aka potatowagon
Author-email: e0007652@u.nus.edu
License: UNKNOWN
Keywords: copinicoos,copernicus,downloader,radar,ESA,EU,satellite,sentinel,sar,download,manager,image,data
Platform: UNKNOWN
Requires-Python: >=3.4
Requires-Dist: colorama (>=0.3.4)
Requires-Dist: cryptography
Provides-Extra: dev
Requires-Dist: codecov (>=2.0.15) ; extra == 'dev'
Requires-Dist: colorama (>=0.3.4) ; extra == 'dev'
Requires-Dist: tox (>=3.9.0) ; extra == 'dev'
Requires-Dist: tox-travis (>=0.12) ; extra == 'dev'
Requires-Dist: pytest (>=4.6.2) ; extra == 'dev'
Requires-Dist: pytest-cov (>=2.7.1) ; extra == 'dev'
Requires-Dist: Pillow (>=5.0.0) ; extra == 'dev'
Requires-Dist: psutil ; extra == 'dev'
